{
  "closestApproach": {
    "distance": 1.44,
    "altitude": 37575,
    "speed": 455,
    "timestamp": "2026-02-01T22:25:36.051Z",
    "lat": 45.6122,
    "lon": -122.4993,
    "precision": "tracked"
  },
  "flight": {
    "callsign": "ASA548",
    "aircraftType": "737",
    "origin": "SNA",
    "destination": "SEA",
    "firstSeen": "2026-01-31T22:24:57.030Z"
  },
  "overheadScore": 1.44,
  "isOverhead": false,
  "pathSnapshots": 1,
  "status": "tracking",
  "timestamp": "2026-02-01T22:25:36.052Z"
}