{
  "closestApproach": {
    "distance": 0.76,
    "altitude": 38000,
    "speed": 427,
    "timestamp": "2026-02-04T01:52:29.928Z",
    "lat": 45.6289,
    "lon": -122.5107,
    "precision": "tracked"
  },
  "flight": {
    "callsign": "ASA760",
    "aircraftType": "737",
    "origin": "SNA",
    "destination": "SEA",
    "firstSeen": "2026-02-04T01:52:29.924Z"
  },
  "overheadScore": 0.76,
  "isOverhead": true,
  "pathSnapshots": 1,
  "status": "tracking",
  "timestamp": "2026-02-04T01:52:29.928Z"
}