{
  "closestApproach": {
    "distance": 1.39,
    "altitude": 38375,
    "speed": 406,
    "timestamp": "2026-02-02T16:24:32.541Z",
    "lat": 45.6251,
    "lon": -122.5613,
    "precision": "tracked"
  },
  "flight": {
    "callsign": "SWA862",
    "aircraftType": "737 ",
    "origin": "SJC",
    "destination": "SEA",
    "firstSeen": "2026-02-02T16:24:32.540Z"
  },
  "overheadScore": 1.39,
  "isOverhead": false,
  "pathSnapshots": 1,
  "status": "completed",
  "timestamp": "2026-02-02T16:25:30.616Z"
}