{
  "closestApproach": {
    "distance": 0.37,
    "altitude": 3400,
    "speed": 110,
    "timestamp": "2026-04-05T02:36:59.144Z",
    "lat": 45.6193,
    "lon": -122.5305,
    "precision": "high"
  },
  "flight": {
    "callsign": "N62407",
    "aircraftType": "C172",
    "origin": null,
    "destination": null,
    "firstSeen": "2026-04-05T02:36:38.567Z"
  },
  "overheadScore": 0.37,
  "isOverhead": true,
  "pathSnapshots": 4,
  "trail": [
    [
      45.62,
      -122.5165
    ],
    [
      45.6197,
      -122.5223
    ],
    [
      45.6193,
      -122.5305
    ],
    [
      45.6188,
      -122.5383
    ]
  ],
  "status": "completed",
  "timestamp": "2026-04-05T02:37:19.758Z"
}