{
  "closestApproach": {
    "distance": 0.55,
    "altitude": 2500,
    "speed": 95,
    "timestamp": "2026-03-01T01:16:25.680Z",
    "lat": 45.6345,
    "lon": -122.5286,
    "precision": "high"
  },
  "flight": {
    "callsign": "N4466R",
    "aircraftType": "C172",
    "origin": null,
    "destination": null,
    "firstSeen": "2026-03-01T01:16:04.720Z"
  },
  "overheadScore": 0.55,
  "isOverhead": true,
  "pathSnapshots": 4,
  "trail": [
    [
      45.6341,
      -122.5179
    ],
    [
      45.6343,
      -122.5223
    ],
    [
      45.6345,
      -122.5286
    ],
    [
      45.6346,
      -122.536
    ]
  ],
  "status": "completed",
  "timestamp": "2026-03-01T01:16:46.695Z"
}