{
  "closestApproach": {
    "distance": 0.49,
    "altitude": 30000,
    "speed": 402,
    "timestamp": "2026-02-02T21:13:48.584Z",
    "lat": 45.6177,
    "lon": -122.5238,
    "precision": "tracked"
  },
  "flight": {
    "callsign": "DAL2922",
    "aircraftType": "737",
    "origin": "LAS",
    "destination": "SEA",
    "firstSeen": "2026-02-02T21:13:48.582Z"
  },
  "overheadScore": 0.49,
  "isOverhead": true,
  "pathSnapshots": 1,
  "status": "tracking",
  "timestamp": "2026-02-02T21:13:48.584Z"
}