{
  "closestApproach": {
    "distance": 0.83,
    "altitude": 28000,
    "speed": 447,
    "timestamp": "2026-02-08T23:39:11.674Z",
    "lat": 45.6251,
    "lon": -122.5084,
    "precision": "tracked"
  },
  "flight": {
    "callsign": "ASA741",
    "aircraftType": "737 ",
    "origin": "LAS",
    "destination": "SEA",
    "firstSeen": "2026-02-08T23:39:11.667Z"
  },
  "overheadScore": 0.83,
  "isOverhead": true,
  "pathSnapshots": 1,
  "status": "tracking",
  "timestamp": "2026-02-08T23:39:11.674Z"
}