{
  "closestApproach": {
    "distance": 0.54,
    "altitude": 2925,
    "speed": 108,
    "timestamp": "2026-03-18T18:53:49.601Z",
    "lat": 45.6284,
    "lon": -122.516,
    "precision": "tracked"
  },
  "flight": {
    "callsign": "N473TW",
    "aircraftType": "Cara",
    "origin": "TTD",
    "destination": null,
    "firstSeen": "2026-03-16T23:19:19.312Z"
  },
  "overheadScore": 0.54,
  "isOverhead": true,
  "pathSnapshots": 1,
  "trail": [
    [
      45.6284,
      -122.516
    ]
  ],
  "status": "tracking",
  "timestamp": "2026-03-18T18:53:49.601Z"
}