{
  "closestApproach": {
    "distance": 0.44,
    "altitude": 3350,
    "speed": 91,
    "timestamp": "2026-03-19T14:57:59.009Z",
    "lat": 45.6223,
    "lon": -122.5376,
    "precision": "tracked"
  },
  "flight": {
    "callsign": "GFY1193",
    "aircraftType": "RV12",
    "origin": null,
    "destination": null,
    "firstSeen": "2026-03-19T14:57:59.005Z"
  },
  "overheadScore": 0.44,
  "isOverhead": true,
  "pathSnapshots": 1,
  "trail": [
    [
      45.6223,
      -122.5376
    ]
  ],
  "status": "tracking",
  "timestamp": "2026-03-19T14:57:59.010Z"
}