{
  "closestApproach": {
    "distance": 1.33,
    "altitude": 34000,
    "speed": 425,
    "timestamp": "2026-02-02T23:08:19.302Z",
    "lat": 45.6236,
    "lon": -122.5598,
    "precision": "tracked"
  },
  "flight": {
    "callsign": "UAL1008",
    "aircraftType": "B39M",
    "origin": "SFO",
    "destination": "SEA",
    "firstSeen": "2026-02-02T23:08:19.300Z"
  },
  "overheadScore": 1.33,
  "isOverhead": false,
  "pathSnapshots": 1,
  "status": "tracking",
  "timestamp": "2026-02-02T23:08:19.302Z"
}