{
  "closestApproach": {
    "distance": 1.39,
    "altitude": 1875,
    "speed": 161,
    "timestamp": "2026-02-01T21:59:06.165Z",
    "lat": 45.6061,
    "lon": -122.5097,
    "precision": "tracked"
  },
  "flight": {
    "callsign": "PC12",
    "aircraftType": "PC-1",
    "origin": null,
    "destination": null,
    "firstSeen": "2026-02-01T21:59:06.164Z"
  },
  "overheadScore": 1.39,
  "isOverhead": false,
  "pathSnapshots": 1,
  "status": "completed",
  "timestamp": "2026-02-01T22:00:02.784Z"
}