{
  "closestApproach": {
    "distance": 0.94,
    "altitude": 35975,
    "speed": 437,
    "timestamp": "2026-01-31T23:18:37.871Z",
    "lat": 45.6225,
    "lon": -122.5061,
    "precision": "tracked"
  },
  "flight": {
    "callsign": "SKW5403",
    "aircraftType": "E175",
    "origin": "LAX",
    "destination": "SEA",
    "firstSeen": "2026-01-31T23:18:37.870Z"
  },
  "overheadScore": 0.94,
  "isOverhead": true,
  "pathSnapshots": 1,
  "status": "completed",
  "timestamp": "2026-01-31T23:19:42.350Z"
}