{
  "closestApproach": {
    "distance": 0.67,
    "altitude": 34000,
    "speed": 395,
    "timestamp": "2026-03-17T02:41:27.940Z",
    "lat": 45.6363,
    "lon": -122.5252,
    "precision": "tracked"
  },
  "flight": {
    "callsign": "SKW4100",
    "aircraftType": "E175",
    "origin": "SJC",
    "destination": "SEA",
    "firstSeen": "2026-02-10T03:47:40.995Z"
  },
  "overheadScore": 0.67,
  "isOverhead": true,
  "pathSnapshots": 1,
  "trail": [
    [
      45.6363,
      -122.5252
    ]
  ],
  "status": "completed",
  "timestamp": "2026-03-17T02:41:38.210Z"
}