{
  "closestApproach": {
    "distance": 0.98,
    "altitude": 33275,
    "speed": 487,
    "timestamp": "2026-02-01T06:32:42.340Z",
    "lat": 45.6225,
    "lon": -122.505,
    "precision": "tracked"
  },
  "flight": {
    "callsign": "ASA532",
    "aircraftType": "B39M",
    "origin": "LAX",
    "destination": "SEA",
    "firstSeen": "2026-01-31T05:55:59.558Z"
  },
  "overheadScore": 0.98,
  "isOverhead": true,
  "pathSnapshots": 1,
  "status": "tracking",
  "timestamp": "2026-02-01T06:32:42.340Z"
}