{
  "closestApproach": {
    "distance": 1.39,
    "altitude": 2075,
    "speed": 117,
    "timestamp": "2026-02-04T00:17:40.530Z",
    "lat": 45.6042,
    "lon": -122.5142,
    "precision": "tracked"
  },
  "flight": {
    "callsign": "N12648",
    "aircraftType": "C172",
    "origin": "TTD",
    "destination": null,
    "firstSeen": "2026-02-04T00:17:40.527Z"
  },
  "overheadScore": 1.39,
  "isOverhead": false,
  "pathSnapshots": 1,
  "status": "tracking",
  "timestamp": "2026-02-04T00:17:40.530Z"
}