{
  "closestApproach": {
    "distance": 1.33,
    "altitude": 800,
    "speed": 98,
    "timestamp": "2026-02-09T23:58:25.959Z",
    "lat": 45.6335,
    "lon": -122.5574,
    "precision": "tracked"
  },
  "flight": {
    "callsign": "N5107H",
    "aircraftType": "C172",
    "origin": "TTD",
    "destination": null,
    "firstSeen": "2026-02-09T23:58:25.954Z"
  },
  "overheadScore": 1.33,
  "isOverhead": false,
  "pathSnapshots": 1,
  "status": "tracking",
  "timestamp": "2026-02-09T23:58:25.959Z"
}