{
  "closestApproach": {
    "distance": 1.44,
    "altitude": 24000,
    "speed": 390,
    "timestamp": "2026-02-09T21:31:30.130Z",
    "lat": 45.6285,
    "lon": -122.562,
    "precision": "tracked"
  },
  "flight": {
    "callsign": "DAL8804",
    "aircraftType": "737",
    "origin": "SFO",
    "destination": "SEA",
    "firstSeen": "2026-02-09T21:31:30.124Z"
  },
  "overheadScore": 1.44,
  "isOverhead": false,
  "pathSnapshots": 1,
  "status": "completed",
  "timestamp": "2026-02-09T21:32:28.835Z"
}