{
  "closestApproach": {
    "distance": 1.41,
    "altitude": 1300,
    "speed": 78,
    "timestamp": "2026-01-31T21:26:55.412Z",
    "lat": 45.6193,
    "lon": -122.5605,
    "precision": "tracked"
  },
  "flight": {
    "callsign": "N5201H",
    "aircraftType": "C172",
    "origin": "TTD",
    "destination": null,
    "firstSeen": "2026-01-30T20:33:02.235Z"
  },
  "overheadScore": 1.41,
  "isOverhead": false,
  "pathSnapshots": 1,
  "status": "tracking",
  "timestamp": "2026-01-31T21:26:55.412Z"
}