{
  "closestApproach": {
    "distance": 1.37,
    "altitude": 38000,
    "speed": 471,
    "timestamp": "2026-02-10T03:24:35.379Z",
    "lat": 45.6273,
    "lon": -122.5607,
    "precision": "tracked"
  },
  "flight": {
    "callsign": "ABX3111",
    "aircraftType": "767",
    "origin": "SCK",
    "destination": "SEA",
    "firstSeen": "2026-02-10T03:24:35.374Z"
  },
  "overheadScore": 1.37,
  "isOverhead": false,
  "pathSnapshots": 1,
  "status": "tracking",
  "timestamp": "2026-02-10T03:24:35.381Z"
}