{
  "closestApproach": {
    "distance": 1.44,
    "altitude": 37400,
    "speed": 434,
    "timestamp": "2026-02-08T15:09:03.791Z",
    "lat": 45.6129,
    "lon": -122.5576,
    "precision": "tracked"
  },
  "flight": {
    "callsign": "DAL2721",
    "aircraftType": "A223",
    "origin": "SFO",
    "destination": "SEA",
    "firstSeen": "2026-02-08T15:09:03.785Z"
  },
  "overheadScore": 1.44,
  "isOverhead": false,
  "pathSnapshots": 1,
  "status": "tracking",
  "timestamp": "2026-02-08T15:09:03.791Z"
}