{
  "closestApproach": {
    "distance": 0.86,
    "altitude": 34000,
    "speed": 481,
    "timestamp": "2026-02-06T20:21:25.470Z",
    "lat": 45.6244,
    "lon": -122.5076,
    "precision": "tracked"
  },
  "flight": {
    "callsign": "ASA1378",
    "aircraftType": "737",
    "origin": "SNA",
    "destination": "SEA",
    "firstSeen": "2026-02-06T20:21:25.466Z"
  },
  "overheadScore": 0.86,
  "isOverhead": true,
  "pathSnapshots": 1,
  "status": "completed",
  "timestamp": "2026-02-06T20:22:23.722Z"
}