{
  "closestApproach": {
    "distance": 0.38,
    "altitude": 1800,
    "speed": 98,
    "timestamp": "2026-02-26T20:18:27.736Z",
    "lat": 45.6299,
    "lon": -122.5218,
    "precision": "high"
  },
  "flight": {
    "callsign": "N6758H",
    "aircraftType": "C172",
    "origin": "TTD",
    "destination": null,
    "firstSeen": "2026-01-31T19:49:55.976Z"
  },
  "overheadScore": 0.38,
  "isOverhead": true,
  "pathSnapshots": 4,
  "trail": [
    [
      45.6339,
      -122.5256
    ],
    [
      45.6299,
      -122.5218
    ],
    [
      45.6256,
      -122.5183
    ],
    [
      45.6225,
      -122.5154
    ]
  ],
  "status": "completed",
  "timestamp": "2026-02-26T20:18:58.642Z"
}