{
  "closestApproach": {
    "distance": 0.33,
    "altitude": 1850,
    "speed": 85,
    "timestamp": "2026-03-27T15:43:15.817Z",
    "lat": 45.6299,
    "lon": -122.5323,
    "precision": "high"
  },
  "flight": {
    "callsign": "N20640",
    "aircraftType": "C180",
    "origin": "TTD",
    "destination": null,
    "firstSeen": "2026-02-27T21:58:04.037Z"
  },
  "overheadScore": 0.33,
  "isOverhead": true,
  "pathSnapshots": 6,
  "trail": [
    [
      45.6321,
      -122.5162
    ],
    [
      45.6322,
      -122.5215
    ],
    [
      45.6316,
      -122.5272
    ],
    [
      45.6299,
      -122.5323
    ],
    [
      45.6273,
      -122.5377
    ],
    [
      45.6245,
      -122.5431
    ]
  ],
  "status": "completed",
  "timestamp": "2026-03-27T15:43:46.618Z"
}