{
  "closestApproach": {
    "distance": 1.43,
    "altitude": 34000,
    "speed": 437,
    "timestamp": "2026-02-01T18:25:52.684Z",
    "lat": 45.6121,
    "lon": -122.4998,
    "precision": "tracked"
  },
  "flight": {
    "callsign": "DAL1293",
    "aircraftType": "A220",
    "origin": "SNA",
    "destination": "SEA",
    "firstSeen": "2026-01-31T17:24:18.334Z"
  },
  "overheadScore": 1.43,
  "isOverhead": false,
  "pathSnapshots": 1,
  "status": "tracking",
  "timestamp": "2026-02-01T18:25:52.684Z"
}