{
  "closestApproach": {
    "distance": 0.61,
    "altitude": 1325,
    "speed": 142,
    "timestamp": "2026-02-25T22:15:02.769Z",
    "lat": 45.6354,
    "lon": -122.529,
    "precision": "tracked"
  },
  "flight": {
    "callsign": "N2123Y",
    "aircraftType": "C182",
    "origin": "PDX",
    "destination": null,
    "firstSeen": "2026-02-25T22:15:02.685Z"
  },
  "overheadScore": 0.61,
  "isOverhead": true,
  "pathSnapshots": 2,
  "trail": [
    [
      45.6354,
      -122.529
    ],
    [
      45.6345,
      -122.519
    ]
  ],
  "status": "completed",
  "timestamp": "2026-02-25T22:15:23.346Z"
}