{
  "closestApproach": {
    "distance": 1.45,
    "altitude": 37725,
    "speed": 467,
    "timestamp": "2026-02-05T04:30:05.491Z",
    "lat": 45.636,
    "lon": -122.4972,
    "precision": "tracked"
  },
  "flight": {
    "callsign": "DAL2955",
    "aircraftType": "737",
    "origin": "LAS",
    "destination": "SEA",
    "firstSeen": "2026-02-05T04:30:05.486Z"
  },
  "overheadScore": 1.45,
  "isOverhead": false,
  "pathSnapshots": 1,
  "status": "tracking",
  "timestamp": "2026-02-05T04:30:05.491Z"
}