{
  "closestApproach": {
    "distance": 1.37,
    "altitude": 35475,
    "speed": 475,
    "timestamp": "2026-02-06T17:19:20.259Z",
    "lat": 45.6343,
    "lon": -122.5581,
    "precision": "tracked"
  },
  "flight": {
    "callsign": "DAL1293",
    "aircraftType": "A220",
    "origin": "SNA",
    "destination": "SEA",
    "firstSeen": "2026-02-06T17:19:20.256Z"
  },
  "overheadScore": 1.37,
  "isOverhead": false,
  "pathSnapshots": 1,
  "status": "completed",
  "timestamp": "2026-02-06T17:20:18.002Z"
}