{
  "closestApproach": {
    "distance": 0.7,
    "altitude": 33975,
    "speed": 484,
    "timestamp": "2026-02-06T01:35:42.303Z",
    "lat": 45.6232,
    "lon": -122.5117,
    "precision": "tracked"
  },
  "flight": {
    "callsign": "DAL1412",
    "aircraftType": "A220",
    "origin": "SFO",
    "destination": "SEA",
    "firstSeen": "2026-02-06T01:35:42.301Z"
  },
  "overheadScore": 0.7,
  "isOverhead": true,
  "pathSnapshots": 2,
  "status": "tracking",
  "timestamp": "2026-02-06T01:36:40.425Z"
}