{
  "closestApproach": {
    "distance": 0.43,
    "altitude": 24000,
    "speed": 239,
    "timestamp": "2026-02-26T21:19:18.636Z",
    "lat": 45.6183,
    "lon": -122.5256,
    "precision": "tracked"
  },
  "flight": {
    "callsign": "BE20",
    "aircraftType": "King",
    "origin": null,
    "destination": null,
    "firstSeen": "2026-02-17T01:56:39.910Z"
  },
  "overheadScore": 0.43,
  "isOverhead": true,
  "pathSnapshots": 1,
  "trail": [
    [
      45.6183,
      -122.5256
    ]
  ],
  "status": "tracking",
  "timestamp": "2026-02-26T21:19:18.636Z"
}